codes/control components/full control and testbenchs/control testbench/control.v
module SR_latch(r, s, q);
  input wire r, s;
  output wire q;
  reg rq = 0;
  
  assign q = rq;
  
  always @(r, s)
    begin
      if(r && s || !r && !s)
        begin
          // condition to ignore
        end
      else if(r && !s)
        begin
          rq = 0;
        end
      else if(!r && s)
        begin
          rq = 1;
        end
    end
endmodule


module control(start , stop , clear, closed_door, finished_time, magnetron);

  input wire start, stop, clear, closed_door, finished_time;
  output wire magnetron;
  wire rs, rr, rq;
  
  assign rs = ((!start  && closed_door)) ? 1 : 0;
  assign rr = ((!stop || finished_time || !closed_door || !clear)) ? 1 : 0;
  
  SR_latch latch(.r(rr), .s(rs), .q(rq));
  assign magnetron = rq;
endmodule

codes/control components/full control and testbenchs/control testbench/control_tb.v
`timescale 1ns/1ps
module control_tb();
  
  reg start, stop, clear , closed_door, finished_time;
  wire magnetron;

  control DUT(
    .start(start), .stop(stop), .clear(clear),
    .closed_door(closed_door), .finished_time(finished_time),
    .magnetron(magnetron)  
  );
  
  initial
    begin
      $dumpfile("testbench_control.vcd");
      $dumpvars(0, control_tb);

      start = 0; stop = 0; clear = 0; finished_time = 0; closed_door = 0;
      #10 start = 1; stop = 1; clear = 1; finished_time = 1; closed_door = 0;   
      #10 start = 1; stop = 1; clear = 1; finished_time = 1; closed_door = 0;   
      #10 start = 1; stop = 1; clear = 1; finished_time = 1; closed_door = 0;   
      #10 start = 1; stop = 1; clear = 1; finished_time = 0; closed_door = 0;   
      #10 start = 1; stop = 1; clear = 1; finished_time = 0; closed_door = 0;   
      #10 start = 1; stop = 0; clear = 1; finished_time = 0; closed_door = 0;   
      #10 start = 1; stop = 0; clear = 1; finished_time = 0; closed_door = 0;   
      #10 start = 1; stop = 0; clear = 1; finished_time = 0; closed_door = 0;   

      #10 start=0; stop=1; clear=1; finished_time=0; closed_door=0;   
      #10 start=0; stop=1; clear=1; finished_time=0; closed_door=1;   
      #10 start=0; stop=1; clear=1; finished_time=1; closed_door=0;   
      #10 start=0; stop=1; clear=1; finished_time=1; closed_door=1;   
      #10 start=0; stop=1; clear=1; finished_time=0; closed_door=0;   
      #10 start=1; stop=1; clear=1; finished_time=0; closed_door=1;   
      #10 start=1; stop=1; clear=1; finished_time=1; closed_door=0;   
      #10 start=1; stop=1; clear=1; finished_time=1; closed_door=1;   

      #10 start = 1; stop = 1; clear = 1; finished_time = 0; closed_door = 1;   
      #50 start = 0; stop = 1; clear = 1; finished_time = 0; closed_door = 1;   
      #5  start = 1; stop = 1; clear = 1; finished_time = 0; closed_door = 1;   
      #50 start = 1; stop = 1; clear = 1; finished_time = 1; closed_door = 1;   
      #50 start = 1; stop = 1; clear = 1; finished_time = 1; closed_door = 0;
    end
endmodule

codes/control components/full control and testbenchs/control testbench/testbench_control.vcd
$date
	Fri Aug 27 19:15:01 2021
$end
$version
	Icarus Verilog
$end
$timescale
	1ps
$end
$scope module control_tb $end
$var wire 1 ! magnetron $end
$var reg 1 " clear $end
$var reg 1 # closed_door $end
$var reg 1 $ finished_time $end
$var reg 1 % start $end
$var reg 1 & stop $end
$scope module DUT $end
$var wire 1 " clear $end
$var wire 1 # closed_door $end
$var wire 1 $ finished_time $end
$var wire 1 ! magnetron $end
$var wire 1 % start $end
$var wire 1 & stop $end
$var wire 1 ' rs $end
$var wire 1 ( rr $end
$var wire 1 ) rq $end
$scope module latch $end
$var wire 1 ( r $end
$var wire 1 ' s $end
$var wire 1 ) q $end
$var reg 1 ) rq $end
$upscope $end
$upscope $end
$upscope $end
$enddefinitions $end
#0
$dumpvars
0)
1(
0'
0&
0%
0$
0#
0"
0!
$end
#10000
1$
1"
1&
1%
#40000
0$
#60000
0&
#90000
1&
0%
#100000
1!
1)
0(
1'
1#
#110000
0!
0)
1(
0'
0#
1$
#120000
1'
1#
#130000
0'
0#
0$
#140000
0(
1#
1%
#150000
1(
0#
1$
#160000
1#
#170000
0(
0$
#220000
1!
1)
1'
0%
#225000
0'
1%
#275000
0!
0)
1(
1$
#325000
0#
