codes/decoder_components/full decoder and testbench/decoder.v
module decoder(units_sec, tens_sec, minutes, units_sec_segments, tens_sec_segments, minutes_segments);

  input wire [3:0] units_sec, tens_sec, minutes;
  output wire [6:0] units_sec_segments, tens_sec_segments, minutes_segments;
  
  assign units_sec_segments = (units_sec == 4'b0000) ? 7'b1111110: // 0
                              (units_sec == 4'b0001) ? 7'b0110000: // 1
                              (units_sec == 4'b0010) ? 7'b1101101: // 2 
                              (units_sec == 4'b0011) ? 7'b1111001: // 3
                              (units_sec == 4'b0100) ? 7'b0110011: // 4
                              (units_sec == 4'b0101) ? 7'b1011011: // 5
                              (units_sec == 4'b0110) ? 7'b1011111: // 6
                              (units_sec == 4'b0111) ? 7'b1110000: // 7
                              (units_sec == 4'b1000) ? 7'b1111111: // 8
                              (units_sec == 4'b1001) ? 7'b1110011: // 9
                              8'bXXXX_XXXX;
  
  assign tens_sec_segments = (tens_sec == 4'b0000) ? 7'b1111110: // 0 ->
                             (tens_sec == 4'b0001) ? 7'b0110000: // 1 ->
                             (tens_sec == 4'b0010) ? 7'b1101101: // 2 ->
                             (tens_sec == 4'b0011) ? 7'b1111001: // 3 ->
                             (tens_sec == 4'b0100) ? 7'b0110011: // 4 ->
                             (tens_sec == 4'b0101) ? 7'b1011011: // 5 ->
                             (tens_sec == 4'b0110) ? 7'b1011111: // 6 ->
                             (tens_sec == 4'b0111) ? 7'b1110000: // 7 ->
                             (tens_sec == 4'b1000) ? 7'b1111111: // 8 ->
                             (tens_sec == 4'b1001) ? 7'b1110011: // 9 ->
                             8'bXXXX_XXXX;

  assign minutes_segments = (minutes == 4'b0000) ? 7'b1111110: // 0 ->
                            (minutes == 4'b0001) ? 7'b0110000: // 1 ->
                            (minutes == 4'b0010) ? 7'b1101101: // 2 ->
                            (minutes == 4'b0011) ? 7'b1111001: // 3 ->
                            (minutes == 4'b0100) ? 7'b0110011: // 4 ->
                            (minutes == 4'b0101) ? 7'b1011011: // 5 ->
                            (minutes == 4'b0110) ? 7'b1011111: // 6 ->
                            (minutes == 4'b0111) ? 7'b1110000: // 7 ->
                            (minutes == 4'b1000) ? 7'b1111111: // 8 ->
                            (minutes == 4'b1001) ? 7'b1110011: // 9 ->
                            8'bXXXX_XXXX;
endmodule

codes/decoder_components/full decoder and testbench/decoder_tb.v
`timescale 1ns/1ps
module decoder_tb();
  reg [3:0] units_sec, tens_sec, minutes ;
  wire [6:0] minutes_segments , units_sec_segments , tens_sec_segments ;
  
  decoder DUT(
    .units_sec(units_sec), .tens_sec(tens_sec), .minutes(minutes),
    .units_sec_segments(units_sec_segments) , .tens_sec_segments(tens_sec_segments),
    .minutes_segments(minutes_segments)
  );
  initial
    begin
      $dumpfile("decoder_tb.vcd");
      $dumpvars(0, decoder_tb);
      
      units_sec = 0; tens_sec = 0; minutes = 0;
      
      #10 units_sec = 1; tens_sec = 1; minutes = 0;
      #10 units_sec = 1; tens_sec = 1; minutes = 0;
      #10 units_sec = 1; tens_sec = 1; minutes = 0;
      #10 units_sec = 1; tens_sec = 1; minutes = 0;
      #10 units_sec = 1; tens_sec = 1; minutes = 1;
      #10 units_sec = 1; tens_sec = 1; minutes = 1;
      #10 units_sec = 1; tens_sec = 1; minutes = 1;
      #10 units_sec = 1; tens_sec = 1; minutes = 1;
      
      #10 units_sec = 1; tens_sec = 1; minutes = 0;
      #10 units_sec = 1; tens_sec = 1; minutes = 0;
      #10 units_sec = 1; tens_sec = 1; minutes = 0;
      #10 units_sec = 1; tens_sec = 1; minutes = 0;
      #10 units_sec = 1; tens_sec = 1; minutes = 1;
      #10 units_sec = 1; tens_sec = 1; minutes = 1;
      #10 units_sec = 1; tens_sec = 1; minutes = 1;
      #10 units_sec = 1; tens_sec = 1; minutes = 1;
      
      #10 units_sec = 1; tens_sec = 1; minutes = 1;
      #10 units_sec = 1; tens_sec = 1; minutes = 1;
      #10 units_sec = 1; tens_sec = 1; minutes = 1;
      #10 units_sec = 1; tens_sec = 1; minutes = 1;
      #10 units_sec = 1; tens_sec = 1; minutes = 1;
      #10 units_sec = 1; tens_sec = 0; minutes = 1;
      #10 units_sec = 1; tens_sec = 0; minutes = 1;
      #10 units_sec = 1; tens_sec = 0; minutes = 1;
      
      #10 units_sec = 0; tens_sec = 1; minutes = 1;
      #10 units_sec = 0; tens_sec = 1; minutes = 1;
      #10 units_sec = 0; tens_sec = 1; minutes = 1;
      #10 units_sec = 0; tens_sec = 1; minutes = 1;
      #10 units_sec = 0; tens_sec = 1; minutes = 1;
      #10 units_sec = 1; tens_sec = 1; minutes = 1;
      #10 units_sec = 1; tens_sec = 1; minutes = 1;
      #10 units_sec = 1; tens_sec = 1; minutes = 1;
      
      #10 units_sec = 1; tens_sec = 1; minutes = 1;
      #50 units_sec = 0; tens_sec = 1; minutes = 1;
      #5  units_sec = 1; tens_sec = 1; minutes = 1; 
      #50 units_sec = 1; tens_sec = 1; minutes = 1; 
      #50 units_sec = 1; tens_sec = 1; minutes = 1;  
    end
endmodule

codes/decoder_components/full decoder and testbench/decoder_tb.vcd
$date
	Wed Aug 25 22:21:05 2021
$end
$version
	Icarus Verilog
$end
$timescale
	1ps
$end
$scope module decoder_tb $end
$var wire 7 ! units_sec_segments [6:0] $end
$var wire 7 " tens_sec_segments [6:0] $end
$var wire 7 # minutes_segments [6:0] $end
$var reg 4 $ minutes [3:0] $end
$var reg 4 % tens_sec [3:0] $end
$var reg 4 & units_sec [3:0] $end
$scope module DUT $end
$var wire 4 ' minutes [3:0] $end
$var wire 4 ( tens_sec [3:0] $end
$var wire 4 ) units_sec [3:0] $end
$var wire 7 * units_sec_segments [6:0] $end
$var wire 7 + tens_sec_segments [6:0] $end
$var wire 7 , minutes_segments [6:0] $end
$upscope $end
$upscope $end
$enddefinitions $end
#0
$dumpvars
b1111110 ,
b1111110 +
b1111110 *
b0 )
b0 (
b0 '
b0 &
b0 %
b0 $
b1111110 #
b1111110 "
b1111110 !
$end
#10000
b110000 "
b110000 +
b110000 !
b110000 *
b1 %
b1 (
b1 &
b1 )
#50000
b110000 #
b110000 ,
b1 $
b1 '
#90000
b1111110 #
b1111110 ,
b0 $
b0 '
#130000
b110000 #
b110000 ,
b1 $
b1 '
#220000
b1111110 "
b1111110 +
b0 %
b0 (
#250000
b110000 "
b110000 +
b1111110 !
b1111110 *
b1 %
b1 (
b0 &
b0 )
#300000
b110000 !
b110000 *
b1 &
b1 )
#380000
b1111110 !
b1111110 *
b0 &
b0 )
#385000
b110000 !
b110000 *
b1 &
b1 )
